forum/__init__.py
forum/admin.py
forum/apps.py
forum/backend.py
forum/constants.py
forum/handlers.py
forum/migration_helpers.py
forum/models.py
forum/mongo.py
forum/pagination.py
forum/signals.py
forum/toggles.py
forum/urls.py
forum/utils.py
forum/api/__init__.py
forum/api/commentables.py
forum/api/comments.py
forum/api/flags.py
forum/api/pins.py
forum/api/search.py
forum/api/subscriptions.py
forum/api/threads.py
forum/api/users.py
forum/api/votes.py
forum/backends/__init__.py
forum/backends/backend.py
forum/backends/mongodb/__init__.py
forum/backends/mongodb/api.py
forum/backends/mongodb/base_model.py
forum/backends/mongodb/comments.py
forum/backends/mongodb/contents.py
forum/backends/mongodb/subscriptions.py
forum/backends/mongodb/threads.py
forum/backends/mongodb/users.py
forum/backends/mysql/__init__.py
forum/backends/mysql/api.py
forum/backends/mysql/models.py
forum/management/__init__.py
forum/management/commands/__init__.py
forum/management/commands/delete_unused_forum_indices.py
forum/management/commands/forum_create_mongodb_indexes.py
forum/management/commands/forum_delete_course_from_mongodb.py
forum/management/commands/forum_migrate_course_from_mongodb_to_mysql.py
forum/management/commands/initialize_forum_indices.py
forum/management/commands/rebuild_forum_indices.py
forum/management/commands/validate_forum_indices.py
forum/migrations/0001_initial.py
forum/migrations/0002_alter_readstate_course_id_and_more.py
forum/migrations/0003_alter_commentthread_title.py
forum/migrations/0004_add_author_username_fields.py
forum/migrations/__init__.py
forum/search/__init__.py
forum/search/base.py
forum/search/es.py
forum/search/meilisearch.py
forum/serializers/__init__.py
forum/serializers/comment.py
forum/serializers/contents.py
forum/serializers/custom_datetime.py
forum/serializers/subscriptions.py
forum/serializers/thread.py
forum/serializers/users.py
forum/serializers/votes.py
forum/settings/__init__.py
forum/settings/common.py
forum/settings/devstack.py
openedx_forum-0.4.0.dist-info/licenses/LICENSE.txt
openedx_forum-0.4.0.dist-info/METADATA
openedx_forum-0.4.0.dist-info/WHEEL
openedx_forum-0.4.0.dist-info/entry_points.txt
openedx_forum-0.4.0.dist-info/top_level.txt
openedx_forum-0.4.0.dist-info/RECORD
