Metadata-Version: 2.4
Name: openedx-forum
Version: 0.4.0
Summary: Open edX forum application
Home-page: https://github.com/openedx/forum
Author: Open edX Project
Author-email: oscm@openedx.org
License: AGPL 3.0
Keywords: Python edx
Classifier: Development Status :: 3 - Alpha
Classifier: Framework :: Django
Classifier: Framework :: Django :: 4.2
Classifier: Framework :: Django :: 5.2
Classifier: Intended Audience :: Developers
Classifier: License :: OSI Approved :: GNU Affero General Public License v3 or later (AGPLv3+)
Classifier: Natural Language :: English
Classifier: Programming Language :: Python :: 3
Classifier: Programming Language :: Python :: 3.11
Classifier: Programming Language :: Python :: 3.12
Requires-Python: >=3.8
License-File: LICENSE.txt
Requires-Dist: Django
Requires-Dist: beautifulsoup4
Requires-Dist: djangorestframework
Requires-Dist: edx-search
Requires-Dist: elasticsearch
Requires-Dist: mysqlclient
Requires-Dist: openedx-atlas
Requires-Dist: pymongo
Requires-Dist: requests
Dynamic: author
Dynamic: author-email
Dynamic: classifier
Dynamic: description
Dynamic: description-content-type
Dynamic: home-page
Dynamic: keywords
Dynamic: license
Dynamic: license-file
Dynamic: requires-dist
Dynamic: requires-python
Dynamic: summary
